Helper/HTTPHelper.py
Helper/__init__.py
Helper/emitter.py
Helper/emitter_.py
cry_vs-0.0.2.1.dist-info/LICENSE
cry_vs-0.0.2.1.dist-info/METADATA
cry_vs-0.0.2.1.dist-info/WHEEL
cry_vs-0.0.2.1.dist-info/top_level.txt
cry_vs-0.0.2.1.dist-info/RECORD
