Metadata-Version: 2.1
Name: cry-vs
Version: 0.0.2.1
Summary: A crypto_versus wrapper
Home-page: https://github.com/cry_vs.py
Author: addikted
Author-email: author@example.com
License: UNKNOWN
Project-URL: Bug Tracker, https://github.com/cry_vs.py
Platform: UNKNOWN
Classifier: Programming Language :: Python :: 3
Classifier: License :: OSI Approved :: MIT License
Classifier: Operating System :: OS Independent
Requires-Python: >=3.6
License-File: LICENSE
